./PKG-INFO
./README.md
./__init__.py
./better_math.py
./draw_context.py
./preview_scene.py
./pygame_scene.py
./pygameui.py
./pyproject.toml
./scene_handler.py
./.idea/.gitignore
./.idea/PyGameUI.iml
./.idea/misc.xml
./.idea/modules.xml
./.idea/vcs.xml
./.idea/workspace.xml
./.idea/inspectionProfiles/profiles_settings.xml
./elements/py_button.py
./elements/text.py
./elements/texture.py
./textures/hangman_0.png
./textures/hangman_1.png
./textures/hangman_2.png
./textures/hangman_3.png
./textures/hangman_4.png
./textures/hangman_5.png
./textures/hangman_6.png
./textures/hangman_7.png
./textures/hangman_8.png
./textures/test.png
simple_pygame_ui-0.1.19.dist-info/METADATA
simple_pygame_ui-0.1.19.dist-info/WHEEL
simple_pygame_ui-0.1.19.dist-info/RECORD
