Metadata-Version: 2.4
Name: simple-pygame-ui
Version: 0.1.19
Summary: Simple UI Library for pygame
Author: Villagerzock
License: MIT
Classifier: License :: OSI Approved :: MIT License
Classifier: Operating System :: OS Independent
Classifier: Programming Language :: Python :: 3
Requires-Python: >=3.9
Requires-Dist: pygame<3,>=2.6
